threadspy/__init__.py
threadspy/ai/__init__.py
threadspy/ai/agent.py
threadspy/ai/templates/__init__.py
threadspy/ai/templates/qna.py
threadspy/constants.py
threadspy/threads_api.py
threadspy/types/__init__.py
threadspy/types/candidate.py
threadspy/types/caption.py
threadspy/types/common.py
threadspy/types/extensions.py
threadspy/types/get_suggested_users_response.py
threadspy/types/get_thread_likers_response.py
threadspy/types/get_user_profile_replies_response.py
threadspy/types/get_user_profile_response.py
threadspy/types/get_user_profile_thread_response.py
threadspy/types/get_user_profile_threads_response.py
threadspy/types/image_versions2.py
threadspy/types/media_data.py
threadspy/types/post.py
threadspy/types/quoted_post.py
threadspy/types/reply_facepile_user.py
threadspy/types/reposted_post.py
threadspy/types/share_info.py
threadspy/types/suggested_user.py
threadspy/types/text_post_app_info.py
threadspy/types/thread.py
threadspy/types/thread_data.py
threadspy/types/thread_item.py
threadspy/types/threads_bio_link.py
threadspy/types/threads_hd_profile_pic_version.py
threadspy/types/threads_user.py
threadspy/types/threads_user_summary.py
threadspy/types/user_data.py
threadspy/types/user_profile_data.py
threadspy/types/users.py
threadspy/types/video_version.py
threads_py-0.0.9.dist-info/LICENSE
threads_py-0.0.9.dist-info/METADATA
threads_py-0.0.9.dist-info/WHEEL
threads_py-0.0.9.dist-info/RECORD
