Metadata-Version: 2.1
Name: threads-py
Version: 0.0.9
Summary: Unofficial, Reverse-Engineered Python client for Meta's Threads.
Home-page: https://github.com/junhoyeo/threads-py
License: MIT
Keywords: threads,instagram,facebook,meta,api
Author: Junho Yeo
Author-email: i@junho.io
Requires-Python: >=3.8.1,<4.0
Classifier: License :: OSI Approved :: MIT License
Classifier: Programming Language :: Python :: 3
Classifier: Programming Language :: Python :: 3.9
Classifier: Programming Language :: Python :: 3.10
Classifier: Programming Language :: Python :: 3.11
Requires-Dist: dataclasses (>=0.6,<0.7)
Requires-Dist: dataclasses-json (>=0.5.9,<0.6.0)
Requires-Dist: pycryptodome (>=3.18.0,<4.0.0)
Requires-Dist: requests (>=2.31.0,<3.0.0)
Project-URL: Repository, https://github.com/junhoyeo/threads-py
